dimorfism/__init__.py
dimorfism/adapters.py
dimorfism/cli.py
dimorfism/fit_logistic_regression.py
dimorfism/setup_data.py
dimorfism/write_parameters.py
dimorfism-0.1.0.dist-info/entry_points.txt
dimorfism-0.1.0.dist-info/licenses/LICENSE
dimorfism-0.1.0.dist-info/WHEEL
dimorfism-0.1.0.dist-info/METADATA
dimorfism-0.1.0.dist-info/RECORD
