Metadata-Version: 2.4
Name: dimorfism
Version: 0.1.0
Summary: Dimorfism module
Home-page: https://github.com/IslasGECI/dimorfismo_py
Author: Ciencia de Datos • GECI
Author-email: ciencia.datos@islas.org.mx
Requires-Python: >=3.9
Classifier: License :: OSI Approved :: GNU General Public License v3 or later (GPLv3+)
License-File: LICENSE
Requires-Dist: pandas
Requires-Dist: scikit-learn
Requires-Dist: typer
